nanoko/__init__.py
nanoko/client.py
nanoko/exceptions.py
nanoko/api/__init__.py
nanoko/api/bank.py
nanoko/api/llm.py
nanoko/api/service.py
nanoko/api/user.py
nanoko/models/__init__.py
nanoko/models/assignment.py
nanoko/models/llm.py
nanoko/models/performance.py
nanoko/models/question.py
nanoko/models/user.py
nanoko_python-0.2.1.dist-info/licenses/LICENSE
nanoko_python-0.2.1.dist-info/METADATA
nanoko_python-0.2.1.dist-info/WHEEL
nanoko_python-0.2.1.dist-info/top_level.txt
nanoko_python-0.2.1.dist-info/RECORD
