Metadata-Version: 2.4
Name: nanoko-python
Version: 0.2.1
Summary: Python library for Nanoko API
Requires-Python: >=3.11
License-File: LICENSE
Requires-Dist: httpx>=0.28.1
Requires-Dist: pydantic[email]>=2.11.4
Dynamic: license-file
